schengulator/__init__.py
schengulator/check_days_left.py
schengulator/check_stay.py
schengulator/example_stays.csv
schengulator/get_date.py
schengulator/schengenstay.py
schengulator/stay.py
schengulator/stays_from_csv.py
schengulator/test.py
schengulator-1.0.0.dist-info/LICENSE
schengulator-1.0.0.dist-info/METADATA
schengulator-1.0.0.dist-info/WHEEL
schengulator-1.0.0.dist-info/top_level.txt
schengulator-1.0.0.dist-info/RECORD
