Metadata-Version: 2.2
Name: schengulator
Version: 1.0.0
Summary: A tool to calculate how many days an individual has been in Schengen countries out of a specified 180-day period
Author-email: Penelope How <pennyruthhow@gmail.com>
Maintainer-email: Penelope How <pennyruthhow@gmail.com>
License: MIT
Project-URL: Homepage, https://github.com/PennyHow/schengulator
Project-URL: Bug Tracker, https://github.com/PennyHow/schengulator/issues
Keywords: schengen,travel,movement,europe
Classifier: Programming Language :: Python :: 3
Classifier: License :: OSI Approved :: MIT License
Classifier: Development Status :: 5 - Production/Stable
Classifier: Natural Language :: English
Classifier: Operating System :: OS Independent
Requires-Python: >=3.8
License-File: LICENSE
